googleprint
