Metadata-Version: 1.1
Name: googleprint
Version: 0.1.2
Summary: Simple API for Google Cloud Print
Home-page: https://github.com/jaydensmith/googleprint
Author: Jayden Smith
Author-email: jayden@intelliscale.com.au
License: UNKNOWN
Download-URL: https://github.com/jaydensmith/googleprint/tarball/0.1.2
Platform: UNKNOWN
Classifier: Environment :: Web Environment
Classifier: Intended Audience :: Developers
Classifier: Operating System :: OS Independent
Classifier: Programming Language :: Python
Classifier: Topic :: Internet
Classifier: Topic :: Software Development :: Libraries
